[
  {
    "ContainingType": "ProSolution.API.Controllers.AboutController",
    "Method": "Get",
    "RelativePath": "api/About",
    "HttpMethod": "GET",
    "IsController": true,
    "Order": 0,
    "Parameters": [],
    "ReturnTypes": []
  },
  {
    "ContainingType": "ProSolution.API.Controllers.AboutController",
    "Method": "Update",
    "RelativePath": "api/About",
    "HttpMethod": "PUT",
    "IsController": true,
    "Order": 0,
    "Parameters": [
      {
        "Name": "Title",
        "Type": "System.String",
        "IsRequired": false
      },
      {
        "Name": "Description",
        "Type": "System.String",
        "IsRequired": false
      },
      {
        "Name": "Image",
        "Type": "Microsoft.AspNetCore.Http.IFormFile",
        "IsRequired": false
      }
    ],
    "ReturnTypes": []
  },
  {
    "ContainingType": "ProSolution.API.Controllers.AppInfoController",
    "Method": "GetAppInfo",
    "RelativePath": "api/AppInfo",
    "HttpMethod": "GET",
    "IsController": true,
    "Order": 0,
    "Parameters": [],
    "ReturnTypes": []
  },
  {
    "ContainingType": "ProSolution.API.Controllers.AuthController",
    "Method": "IsAuthorized",
    "RelativePath": "api/Auth/check-authorize",
    "HttpMethod": "GET",
    "IsController": true,
    "Order": 0,
    "Parameters": [],
    "ReturnTypes": []
  },
  {
    "ContainingType": "ProSolution.API.Controllers.AuthController",
    "Method": "CheckUserRole",
    "RelativePath": "api/Auth/check-role",
    "HttpMethod": "GET",
    "IsController": true,
    "Order": 0,
    "Parameters": [],
    "ReturnTypes": []
  },
  {
    "ContainingType": "ProSolution.API.Controllers.AuthController",
    "Method": "DeleteAccount",
    "RelativePath": "api/Auth/delete",
    "HttpMethod": "DELETE",
    "IsController": true,
    "Order": 0,
    "Parameters": [],
    "ReturnTypes": []
  },
  {
    "ContainingType": "ProSolution.API.Controllers.AuthController",
    "Method": "ForgotPassword",
    "RelativePath": "api/Auth/forgot-password",
    "HttpMethod": "POST",
    "IsController": true,
    "Order": 0,
    "Parameters": [
      {
        "Name": "email",
        "Type": "System.String",
        "IsRequired": true
      }
    ],
    "ReturnTypes": []
  },
  {
    "ContainingType": "ProSolution.API.Controllers.AuthController",
    "Method": "Login",
    "RelativePath": "api/Auth/login",
    "HttpMethod": "POST",
    "IsController": true,
    "Order": 0,
    "Parameters": [
      {
        "Name": "dto",
        "Type": "ProSolution.BL.DTOs.AuthDTOs.LoginDTO",
        "IsRequired": true
      }
    ],
    "ReturnTypes": []
  },
  {
    "ContainingType": "ProSolution.API.Controllers.AuthController",
    "Method": "Register",
    "RelativePath": "api/Auth/register",
    "HttpMethod": "POST",
    "IsController": true,
    "Order": 0,
    "Parameters": [
      {
        "Name": "dto",
        "Type": "ProSolution.BL.DTOs.AuthDTOs.RegisterDTO",
        "IsRequired": true
      }
    ],
    "ReturnTypes": []
  },
  {
    "ContainingType": "ProSolution.API.Controllers.AuthController",
    "Method": "ResetPassword",
    "RelativePath": "api/Auth/reset-password",
    "HttpMethod": "POST",
    "IsController": true,
    "Order": 0,
    "Parameters": [
      {
        "Name": "Email",
        "Type": "System.String",
        "IsRequired": false
      },
      {
        "Name": "Token",
        "Type": "System.String",
        "IsRequired": false
      },
      {
        "Name": "NewPassword",
        "Type": "System.String",
        "IsRequired": false
      },
      {
        "Name": "ConfirmPassword",
        "Type": "System.String",
        "IsRequired": false
      }
    ],
    "ReturnTypes": []
  },
  {
    "ContainingType": "ProSolution.API.Controllers.BadgeController",
    "Method": "GetAll",
    "RelativePath": "api/Badge",
    "HttpMethod": "GET",
    "IsController": true,
    "Order": 0,
    "Parameters": [],
    "ReturnTypes": [
      {
        "Type": "System.Collections.Generic.ICollection\u00601[[ProSolution.BL.DTOs.BadgeDTOs.BadgeListItemDTO, ProSolution.BL, Version=1.0.0.0, Culture=neutral, PublicKeyToken=null]]",
        "MediaTypes": [
          "text/plain",
          "application/json",
          "text/json"
        ],
        "StatusCode": 200
      }
    ]
  },
  {
    "ContainingType": "ProSolution.API.Controllers.BadgeController",
    "Method": "Create",
    "RelativePath": "api/Badge",
    "HttpMethod": "POST",
    "IsController": true,
    "Order": 0,
    "Parameters": [
      {
        "Name": "Description",
        "Type": "System.String",
        "IsRequired": false
      },
      {
        "Name": "Image",
        "Type": "Microsoft.AspNetCore.Http.IFormFile",
        "IsRequired": false
      },
      {
        "Name": "IsSertificate",
        "Type": "System.Boolean",
        "IsRequired": false
      }
    ],
    "ReturnTypes": []
  },
  {
    "ContainingType": "ProSolution.API.Controllers.BadgeController",
    "Method": "Update",
    "RelativePath": "api/Badge/{id}",
    "HttpMethod": "PUT",
    "IsController": true,
    "Order": 0,
    "Parameters": [
      {
        "Name": "id",
        "Type": "System.Int32",
        "IsRequired": true
      },
      {
        "Name": "Description",
        "Type": "System.String",
        "IsRequired": false
      },
      {
        "Name": "Image",
        "Type": "Microsoft.AspNetCore.Http.IFormFile",
        "IsRequired": false
      },
      {
        "Name": "IsSertificate",
        "Type": "System.Boolean",
        "IsRequired": false
      }
    ],
    "ReturnTypes": []
  },
  {
    "ContainingType": "ProSolution.API.Controllers.BadgeController",
    "Method": "HardDelete",
    "RelativePath": "api/Badge/{id}",
    "HttpMethod": "DELETE",
    "IsController": true,
    "Order": 0,
    "Parameters": [
      {
        "Name": "id",
        "Type": "System.Int32",
        "IsRequired": true
      }
    ],
    "ReturnTypes": []
  },
  {
    "ContainingType": "ProSolution.API.Controllers.BadgeController",
    "Method": "GetAllDeleted",
    "RelativePath": "api/Badge/Deleted",
    "HttpMethod": "GET",
    "IsController": true,
    "Order": 0,
    "Parameters": [],
    "ReturnTypes": [
      {
        "Type": "System.Collections.Generic.ICollection\u00601[[ProSolution.BL.DTOs.BadgeDTOs.BadgeListItemDTO, ProSolution.BL, Version=1.0.0.0, Culture=neutral, PublicKeyToken=null]]",
        "MediaTypes": [
          "text/plain",
          "application/json",
          "text/json"
        ],
        "StatusCode": 200
      }
    ]
  },
  {
    "ContainingType": "ProSolution.API.Controllers.BadgeController",
    "Method": "GetPaginated",
    "RelativePath": "api/Badge/Paginated",
    "HttpMethod": "GET",
    "IsController": true,
    "Order": 0,
    "Parameters": [
      {
        "Name": "PageNumber",
        "Type": "System.Int32",
        "IsRequired": false
      },
      {
        "Name": "PageSize",
        "Type": "System.Int32",
        "IsRequired": false
      }
    ],
    "ReturnTypes": []
  },
  {
    "ContainingType": "ProSolution.API.Controllers.BadgeController",
    "Method": "Restore",
    "RelativePath": "api/Badge/restore/{id}",
    "HttpMethod": "PATCH",
    "IsController": true,
    "Order": 0,
    "Parameters": [
      {
        "Name": "id",
        "Type": "System.Int32",
        "IsRequired": true
      }
    ],
    "ReturnTypes": []
  },
  {
    "ContainingType": "ProSolution.API.Controllers.BadgeController",
    "Method": "SoftDelete",
    "RelativePath": "api/Badge/soft-delete/{id}",
    "HttpMethod": "PATCH",
    "IsController": true,
    "Order": 0,
    "Parameters": [
      {
        "Name": "id",
        "Type": "System.Int32",
        "IsRequired": true
      }
    ],
    "ReturnTypes": []
  },
  {
    "ContainingType": "ProSolution.API.Controllers.BrandController",
    "Method": "GetAll",
    "RelativePath": "api/Brand",
    "HttpMethod": "GET",
    "IsController": true,
    "Order": 0,
    "Parameters": [],
    "ReturnTypes": [
      {
        "Type": "System.Collections.Generic.ICollection\u00601[[ProSolution.Core.Entities.Brand, ProSolution.Core, Version=1.0.0.0, Culture=neutral, PublicKeyToken=null]]",
        "MediaTypes": [
          "text/plain",
          "application/json",
          "text/json"
        ],
        "StatusCode": 200
      }
    ]
  },
  {
    "ContainingType": "ProSolution.API.Controllers.BrandController",
    "Method": "Create",
    "RelativePath": "api/Brand",
    "HttpMethod": "POST",
    "IsController": true,
    "Order": 0,
    "Parameters": [
      {
        "Name": "ImagePath",
        "Type": "Microsoft.AspNetCore.Http.IFormFile",
        "IsRequired": false
      },
      {
        "Name": "Title",
        "Type": "System.String",
        "IsRequired": false
      },
      {
        "Name": "Description",
        "Type": "System.String",
        "IsRequired": false
      }
    ],
    "ReturnTypes": []
  },
  {
    "ContainingType": "ProSolution.API.Controllers.BrandController",
    "Method": "GetById",
    "RelativePath": "api/Brand/{id}",
    "HttpMethod": "GET",
    "IsController": true,
    "Order": 0,
    "Parameters": [
      {
        "Name": "id",
        "Type": "System.Int32",
        "IsRequired": true
      }
    ],
    "ReturnTypes": []
  },
  {
    "ContainingType": "ProSolution.API.Controllers.BrandController",
    "Method": "Update",
    "RelativePath": "api/Brand/{id}",
    "HttpMethod": "PUT",
    "IsController": true,
    "Order": 0,
    "Parameters": [
      {
        "Name": "id",
        "Type": "System.Int32",
        "IsRequired": true
      },
      {
        "Name": "ImagePath",
        "Type": "Microsoft.AspNetCore.Http.IFormFile",
        "IsRequired": false
      },
      {
        "Name": "Title",
        "Type": "System.String",
        "IsRequired": false
      },
      {
        "Name": "Description",
        "Type": "System.String",
        "IsRequired": false
      }
    ],
    "ReturnTypes": []
  },
  {
    "ContainingType": "ProSolution.API.Controllers.BrandController",
    "Method": "HardDelete",
    "RelativePath": "api/Brand/{id}Hard",
    "HttpMethod": "DELETE",
    "IsController": true,
    "Order": 0,
    "Parameters": [
      {
        "Name": "id",
        "Type": "System.Int32",
        "IsRequired": true
      }
    ],
    "ReturnTypes": []
  },
  {
    "ContainingType": "ProSolution.API.Controllers.BrandController",
    "Method": "Restore",
    "RelativePath": "api/Brand/{id}Restore",
    "HttpMethod": "PUT",
    "IsController": true,
    "Order": 0,
    "Parameters": [
      {
        "Name": "id",
        "Type": "System.Int32",
        "IsRequired": true
      }
    ],
    "ReturnTypes": []
  },
  {
    "ContainingType": "ProSolution.API.Controllers.BrandController",
    "Method": "SoftDelete",
    "RelativePath": "api/Brand/{id}Soft",
    "HttpMethod": "DELETE",
    "IsController": true,
    "Order": 0,
    "Parameters": [
      {
        "Name": "id",
        "Type": "System.Int32",
        "IsRequired": true
      }
    ],
    "ReturnTypes": []
  },
  {
    "ContainingType": "ProSolution.API.Controllers.BrandController",
    "Method": "GetAllDeleted",
    "RelativePath": "api/Brand/Deleted",
    "HttpMethod": "GET",
    "IsController": true,
    "Order": 0,
    "Parameters": [],
    "ReturnTypes": [
      {
        "Type": "System.Collections.Generic.ICollection\u00601[[ProSolution.Core.Entities.Brand, ProSolution.Core, Version=1.0.0.0, Culture=neutral, PublicKeyToken=null]]",
        "MediaTypes": [
          "text/plain",
          "application/json",
          "text/json"
        ],
        "StatusCode": 200
      }
    ]
  },
  {
    "ContainingType": "ProSolution.API.Controllers.BrandController",
    "Method": "GetPaginated",
    "RelativePath": "api/Brand/Paginated",
    "HttpMethod": "GET",
    "IsController": true,
    "Order": 0,
    "Parameters": [
      {
        "Name": "PageNumber",
        "Type": "System.Int32",
        "IsRequired": false
      },
      {
        "Name": "PageSize",
        "Type": "System.Int32",
        "IsRequired": false
      }
    ],
    "ReturnTypes": []
  },
  {
    "ContainingType": "ProSolution.API.Controllers.CatagoryController",
    "Method": "GetAll",
    "RelativePath": "api/Catagory",
    "HttpMethod": "GET",
    "IsController": true,
    "Order": 0,
    "Parameters": [],
    "ReturnTypes": [
      {
        "Type": "System.Collections.Generic.ICollection\u00601[[ProSolution.Core.Entities.Catagory, ProSolution.Core, Version=1.0.0.0, Culture=neutral, PublicKeyToken=null]]",
        "MediaTypes": [
          "text/plain",
          "application/json",
          "text/json"
        ],
        "StatusCode": 200
      }
    ]
  },
  {
    "ContainingType": "ProSolution.API.Controllers.CatagoryController",
    "Method": "Create",
    "RelativePath": "api/Catagory",
    "HttpMethod": "POST",
    "IsController": true,
    "Order": 0,
    "Parameters": [
      {
        "Name": "Id",
        "Type": "System.Int32",
        "IsRequired": false
      },
      {
        "Name": "Title",
        "Type": "System.String",
        "IsRequired": false
      },
      {
        "Name": "ParentCategoryId",
        "Type": "System.Nullable\u00601[[System.Int32, System.Private.CoreLib, Version=8.0.0.0, Culture=neutral, PublicKeyToken=7cec85d7bea7798e]]",
        "IsRequired": false
      }
    ],
    "ReturnTypes": []
  },
  {
    "ContainingType": "ProSolution.API.Controllers.CatagoryController",
    "Method": "GetById",
    "RelativePath": "api/Catagory/{id}",
    "HttpMethod": "GET",
    "IsController": true,
    "Order": 0,
    "Parameters": [
      {
        "Name": "id",
        "Type": "System.Int32",
        "IsRequired": true
      }
    ],
    "ReturnTypes": []
  },
  {
    "ContainingType": "ProSolution.API.Controllers.CatagoryController",
    "Method": "Update",
    "RelativePath": "api/Catagory/{id}",
    "HttpMethod": "PUT",
    "IsController": true,
    "Order": 0,
    "Parameters": [
      {
        "Name": "id",
        "Type": "System.Int32",
        "IsRequired": true
      },
      {
        "Name": "catagoryDto",
        "Type": "ProSolution.BL.DTOs.CatagoryDTOs.CatagoryDTO",
        "IsRequired": true
      }
    ],
    "ReturnTypes": []
  },
  {
    "ContainingType": "ProSolution.API.Controllers.CatagoryController",
    "Method": "HardDelete",
    "RelativePath": "api/Catagory/{id}Hard",
    "HttpMethod": "DELETE",
    "IsController": true,
    "Order": 0,
    "Parameters": [
      {
        "Name": "id",
        "Type": "System.Int32",
        "IsRequired": true
      }
    ],
    "ReturnTypes": []
  },
  {
    "ContainingType": "ProSolution.API.Controllers.CatagoryController",
    "Method": "Restore",
    "RelativePath": "api/Catagory/{id}Restore",
    "HttpMethod": "PUT",
    "IsController": true,
    "Order": 0,
    "Parameters": [
      {
        "Name": "id",
        "Type": "System.Int32",
        "IsRequired": true
      }
    ],
    "ReturnTypes": []
  },
  {
    "ContainingType": "ProSolution.API.Controllers.CatagoryController",
    "Method": "SoftDelete",
    "RelativePath": "api/Catagory/{id}Soft",
    "HttpMethod": "DELETE",
    "IsController": true,
    "Order": 0,
    "Parameters": [
      {
        "Name": "id",
        "Type": "System.Int32",
        "IsRequired": true
      }
    ],
    "ReturnTypes": []
  },
  {
    "ContainingType": "ProSolution.API.Controllers.CatagoryController",
    "Method": "GetAllDeleted",
    "RelativePath": "api/Catagory/Deleted",
    "HttpMethod": "GET",
    "IsController": true,
    "Order": 0,
    "Parameters": [],
    "ReturnTypes": [
      {
        "Type": "System.Collections.Generic.ICollection\u00601[[ProSolution.Core.Entities.Catagory, ProSolution.Core, Version=1.0.0.0, Culture=neutral, PublicKeyToken=null]]",
        "MediaTypes": [
          "text/plain",
          "application/json",
          "text/json"
        ],
        "StatusCode": 200
      }
    ]
  },
  {
    "ContainingType": "ProSolution.API.Controllers.CatagoryController",
    "Method": "GetPaginated",
    "RelativePath": "api/Catagory/Paginated",
    "HttpMethod": "GET",
    "IsController": true,
    "Order": 0,
    "Parameters": [
      {
        "Name": "PageNumber",
        "Type": "System.Int32",
        "IsRequired": false
      },
      {
        "Name": "PageSize",
        "Type": "System.Int32",
        "IsRequired": false
      }
    ],
    "ReturnTypes": []
  },
  {
    "ContainingType": "ProSolution.API.Controllers.ContactUsController",
    "Method": "SendContactMessage",
    "RelativePath": "api/ContactUs/contact",
    "HttpMethod": "POST",
    "IsController": true,
    "Order": 0,
    "Parameters": [
      {
        "Name": "dto",
        "Type": "ProSolution.BL.DTOs.ContactMessageDTOs.ContactMessageDTO",
        "IsRequired": true
      }
    ],
    "ReturnTypes": []
  },
  {
    "ContainingType": "ProSolution.API.Controllers.OurServiceController",
    "Method": "GetAll",
    "RelativePath": "api/OurService",
    "HttpMethod": "GET",
    "IsController": true,
    "Order": 0,
    "Parameters": [],
    "ReturnTypes": [
      {
        "Type": "System.Collections.Generic.ICollection\u00601[[ProSolution.BL.DTOs.ServiceDTOs.OurServiceListItemDTO, ProSolution.BL, Version=1.0.0.0, Culture=neutral, PublicKeyToken=null]]",
        "MediaTypes": [
          "text/plain",
          "application/json",
          "text/json"
        ],
        "StatusCode": 200
      }
    ]
  },
  {
    "ContainingType": "ProSolution.API.Controllers.OurServiceController",
    "Method": "Create",
    "RelativePath": "api/OurService",
    "HttpMethod": "POST",
    "IsController": true,
    "Order": 0,
    "Parameters": [
      {
        "Name": "Title",
        "Type": "System.String",
        "IsRequired": false
      },
      {
        "Name": "Description",
        "Type": "System.String",
        "IsRequired": false
      },
      {
        "Name": "Image",
        "Type": "Microsoft.AspNetCore.Http.IFormFile",
        "IsRequired": false
      },
      {
        "Name": "ContentTitle",
        "Type": "System.String",
        "IsRequired": false
      },
      {
        "Name": "ContentDescription",
        "Type": "System.String",
        "IsRequired": false
      },
      {
        "Name": "ContentImage",
        "Type": "Microsoft.AspNetCore.Http.IFormFile",
        "IsRequired": false
      }
    ],
    "ReturnTypes": []
  },
  {
    "ContainingType": "ProSolution.API.Controllers.OurServiceController",
    "Method": "GetById",
    "RelativePath": "api/OurService/{id}",
    "HttpMethod": "GET",
    "IsController": true,
    "Order": 0,
    "Parameters": [
      {
        "Name": "id",
        "Type": "System.Int32",
        "IsRequired": true
      }
    ],
    "ReturnTypes": []
  },
  {
    "ContainingType": "ProSolution.API.Controllers.OurServiceController",
    "Method": "Update",
    "RelativePath": "api/OurService/{id}",
    "HttpMethod": "PUT",
    "IsController": true,
    "Order": 0,
    "Parameters": [
      {
        "Name": "id",
        "Type": "System.Int32",
        "IsRequired": true
      },
      {
        "Name": "Title",
        "Type": "System.String",
        "IsRequired": false
      },
      {
        "Name": "Description",
        "Type": "System.String",
        "IsRequired": false
      },
      {
        "Name": "Image",
        "Type": "Microsoft.AspNetCore.Http.IFormFile",
        "IsRequired": false
      },
      {
        "Name": "ContentTitle",
        "Type": "System.String",
        "IsRequired": false
      },
      {
        "Name": "ContentDescription",
        "Type": "System.String",
        "IsRequired": false
      },
      {
        "Name": "UpdateAt",
        "Type": "System.Nullable\u00601[[System.DateTime, System.Private.CoreLib, Version=8.0.0.0, Culture=neutral, PublicKeyToken=7cec85d7bea7798e]]",
        "IsRequired": false
      },
      {
        "Name": "ContentImage",
        "Type": "Microsoft.AspNetCore.Http.IFormFile",
        "IsRequired": false
      }
    ],
    "ReturnTypes": []
  },
  {
    "ContainingType": "ProSolution.API.Controllers.OurServiceController",
    "Method": "HardDelete",
    "RelativePath": "api/OurService/{id}",
    "HttpMethod": "DELETE",
    "IsController": true,
    "Order": 0,
    "Parameters": [
      {
        "Name": "id",
        "Type": "System.Int32",
        "IsRequired": true
      }
    ],
    "ReturnTypes": []
  },
  {
    "ContainingType": "ProSolution.API.Controllers.OurServiceController",
    "Method": "GetAllDeleted",
    "RelativePath": "api/OurService/Deleted",
    "HttpMethod": "GET",
    "IsController": true,
    "Order": 0,
    "Parameters": [],
    "ReturnTypes": [
      {
        "Type": "System.Collections.Generic.ICollection\u00601[[ProSolution.BL.DTOs.ServiceDTOs.OurServiceListItemDTO, ProSolution.BL, Version=1.0.0.0, Culture=neutral, PublicKeyToken=null]]",
        "MediaTypes": [
          "text/plain",
          "application/json",
          "text/json"
        ],
        "StatusCode": 200
      }
    ]
  },
  {
    "ContainingType": "ProSolution.API.Controllers.OurServiceController",
    "Method": "GetPaginated",
    "RelativePath": "api/OurService/Paginated",
    "HttpMethod": "GET",
    "IsController": true,
    "Order": 0,
    "Parameters": [
      {
        "Name": "PageNumber",
        "Type": "System.Int32",
        "IsRequired": false
      },
      {
        "Name": "PageSize",
        "Type": "System.Int32",
        "IsRequired": false
      }
    ],
    "ReturnTypes": []
  },
  {
    "ContainingType": "ProSolution.API.Controllers.OurServiceController",
    "Method": "Restore",
    "RelativePath": "api/OurService/restore/{id}",
    "HttpMethod": "PATCH",
    "IsController": true,
    "Order": 0,
    "Parameters": [
      {
        "Name": "id",
        "Type": "System.Int32",
        "IsRequired": true
      }
    ],
    "ReturnTypes": []
  },
  {
    "ContainingType": "ProSolution.API.Controllers.OurServiceController",
    "Method": "Search",
    "RelativePath": "api/OurService/Search",
    "HttpMethod": "GET",
    "IsController": true,
    "Order": 0,
    "Parameters": [
      {
        "Name": "searchword",
        "Type": "System.String",
        "IsRequired": false
      }
    ],
    "ReturnTypes": []
  },
  {
    "ContainingType": "ProSolution.API.Controllers.OurServiceController",
    "Method": "SoftDelete",
    "RelativePath": "api/OurService/soft-delete/{id}",
    "HttpMethod": "PATCH",
    "IsController": true,
    "Order": 0,
    "Parameters": [
      {
        "Name": "id",
        "Type": "System.Int32",
        "IsRequired": true
      }
    ],
    "ReturnTypes": []
  },
  {
    "ContainingType": "ProSolution.API.Controllers.PartnerController",
    "Method": "GetAll",
    "RelativePath": "api/Partner",
    "HttpMethod": "GET",
    "IsController": true,
    "Order": 0,
    "Parameters": [],
    "ReturnTypes": [
      {
        "Type": "System.Collections.Generic.ICollection\u00601[[ProSolution.Core.Entities.Partner, ProSolution.Core, Version=1.0.0.0, Culture=neutral, PublicKeyToken=null]]",
        "MediaTypes": [
          "text/plain",
          "application/json",
          "text/json"
        ],
        "StatusCode": 200
      }
    ]
  },
  {
    "ContainingType": "ProSolution.API.Controllers.PartnerController",
    "Method": "Create",
    "RelativePath": "api/Partner",
    "HttpMethod": "POST",
    "IsController": true,
    "Order": 0,
    "Parameters": [
      {
        "Name": "ImagePath",
        "Type": "Microsoft.AspNetCore.Http.IFormFile",
        "IsRequired": false
      }
    ],
    "ReturnTypes": []
  },
  {
    "ContainingType": "ProSolution.API.Controllers.PartnerController",
    "Method": "GetById",
    "RelativePath": "api/Partner/{id}",
    "HttpMethod": "GET",
    "IsController": true,
    "Order": 0,
    "Parameters": [
      {
        "Name": "id",
        "Type": "System.Int32",
        "IsRequired": true
      }
    ],
    "ReturnTypes": []
  },
  {
    "ContainingType": "ProSolution.API.Controllers.PartnerController",
    "Method": "Update",
    "RelativePath": "api/Partner/{id}",
    "HttpMethod": "PUT",
    "IsController": true,
    "Order": 0,
    "Parameters": [
      {
        "Name": "id",
        "Type": "System.Int32",
        "IsRequired": true
      },
      {
        "Name": "ImagePath",
        "Type": "Microsoft.AspNetCore.Http.IFormFile",
        "IsRequired": false
      }
    ],
    "ReturnTypes": []
  },
  {
    "ContainingType": "ProSolution.API.Controllers.PartnerController",
    "Method": "HardDelete",
    "RelativePath": "api/Partner/{id}Hard",
    "HttpMethod": "DELETE",
    "IsController": true,
    "Order": 0,
    "Parameters": [
      {
        "Name": "id",
        "Type": "System.Int32",
        "IsRequired": true
      }
    ],
    "ReturnTypes": []
  },
  {
    "ContainingType": "ProSolution.API.Controllers.PartnerController",
    "Method": "Restore",
    "RelativePath": "api/Partner/{id}Restore",
    "HttpMethod": "PUT",
    "IsController": true,
    "Order": 0,
    "Parameters": [
      {
        "Name": "id",
        "Type": "System.Int32",
        "IsRequired": true
      }
    ],
    "ReturnTypes": []
  },
  {
    "ContainingType": "ProSolution.API.Controllers.PartnerController",
    "Method": "SoftDelete",
    "RelativePath": "api/Partner/{id}Soft",
    "HttpMethod": "DELETE",
    "IsController": true,
    "Order": 0,
    "Parameters": [
      {
        "Name": "id",
        "Type": "System.Int32",
        "IsRequired": true
      }
    ],
    "ReturnTypes": []
  },
  {
    "ContainingType": "ProSolution.API.Controllers.PartnerController",
    "Method": "GetAllDeleted",
    "RelativePath": "api/Partner/Deleted",
    "HttpMethod": "GET",
    "IsController": true,
    "Order": 0,
    "Parameters": [],
    "ReturnTypes": [
      {
        "Type": "System.Collections.Generic.ICollection\u00601[[ProSolution.Core.Entities.Partner, ProSolution.Core, Version=1.0.0.0, Culture=neutral, PublicKeyToken=null]]",
        "MediaTypes": [
          "text/plain",
          "application/json",
          "text/json"
        ],
        "StatusCode": 200
      }
    ]
  },
  {
    "ContainingType": "ProSolution.API.Controllers.PartnerController",
    "Method": "GetPaginated",
    "RelativePath": "api/Partner/Paginated",
    "HttpMethod": "GET",
    "IsController": true,
    "Order": 0,
    "Parameters": [
      {
        "Name": "PageNumber",
        "Type": "System.Int32",
        "IsRequired": false
      },
      {
        "Name": "PageSize",
        "Type": "System.Int32",
        "IsRequired": false
      }
    ],
    "ReturnTypes": []
  },
  {
    "ContainingType": "ProSolution.API.Controllers.ProductController",
    "Method": "GetAll",
    "RelativePath": "api/Product",
    "HttpMethod": "GET",
    "IsController": true,
    "Order": 0,
    "Parameters": [],
    "ReturnTypes": [
      {
        "Type": "System.Collections.Generic.ICollection\u00601[[ProSolution.BL.DTOs.ProductDTOs.ProductReadDTO, ProSolution.BL, Version=1.0.0.0, Culture=neutral, PublicKeyToken=null]]",
        "MediaTypes": [
          "text/plain",
          "application/json",
          "text/json"
        ],
        "StatusCode": 200
      }
    ]
  },
  {
    "ContainingType": "ProSolution.API.Controllers.ProductController",
    "Method": "Create",
    "RelativePath": "api/Product",
    "HttpMethod": "POST",
    "IsController": true,
    "Order": 0,
    "Parameters": [
      {
        "Name": "Title",
        "Type": "System.String",
        "IsRequired": false
      },
      {
        "Name": "Description",
        "Type": "System.String",
        "IsRequired": false
      },
      {
        "Name": "Price",
        "Type": "System.Decimal",
        "IsRequired": false
      },
      {
        "Name": "Images",
        "Type": "System.Collections.Generic.List\u00601[[ProSolution.BL.DTOs.ProductImageDTOs.ProductImageCreateDTO, ProSolution.BL, Version=1.0.0.0, Culture=neutral, PublicKeyToken=null]]",
        "IsRequired": false
      },
      {
        "Name": "CategoryId",
        "Type": "System.Int32",
        "IsRequired": false
      },
      {
        "Name": "Stock",
        "Type": "System.Int32",
        "IsRequired": false
      },
      {
        "Name": "DiscountEndDate",
        "Type": "System.Nullable\u00601[[System.DateTime, System.Private.CoreLib, Version=8.0.0.0, Culture=neutral, PublicKeyToken=7cec85d7bea7798e]]",
        "IsRequired": false
      },
      {
        "Name": "SoldCount",
        "Type": "System.Int32",
        "IsRequired": false
      },
      {
        "Name": "Dicount",
        "Type": "System.Nullable\u00601[[System.Single, System.Private.CoreLib, Version=8.0.0.0, Culture=neutral, PublicKeyToken=7cec85d7bea7798e]]",
        "IsRequired": false
      }
    ],
    "ReturnTypes": []
  },
  {
    "ContainingType": "ProSolution.API.Controllers.ProductController",
    "Method": "Update",
    "RelativePath": "api/Product/{id}",
    "HttpMethod": "PUT",
    "IsController": true,
    "Order": 0,
    "Parameters": [
      {
        "Name": "id",
        "Type": "System.Int32",
        "IsRequired": true
      },
      {
        "Name": "Title",
        "Type": "System.String",
        "IsRequired": false
      },
      {
        "Name": "Description",
        "Type": "System.String",
        "IsRequired": false
      },
      {
        "Name": "Price",
        "Type": "System.Decimal",
        "IsRequired": false
      },
      {
        "Name": "ImagePath",
        "Type": "Microsoft.AspNetCore.Http.IFormFile",
        "IsRequired": false
      },
      {
        "Name": "CategoryId",
        "Type": "System.Int32",
        "IsRequired": false
      },
      {
        "Name": "Stock",
        "Type": "System.Int32",
        "IsRequired": false
      },
      {
        "Name": "SoldCount",
        "Type": "System.Int32",
        "IsRequired": false
      },
      {
        "Name": "Dicount",
        "Type": "System.Nullable\u00601[[System.Single, System.Private.CoreLib, Version=8.0.0.0, Culture=neutral, PublicKeyToken=7cec85d7bea7798e]]",
        "IsRequired": false
      },
      {
        "Name": "DiscountEndDate",
        "Type": "System.Nullable\u00601[[System.DateTime, System.Private.CoreLib, Version=8.0.0.0, Culture=neutral, PublicKeyToken=7cec85d7bea7798e]]",
        "IsRequired": false
      }
    ],
    "ReturnTypes": []
  },
  {
    "ContainingType": "ProSolution.API.Controllers.ProductController",
    "Method": "GetById",
    "RelativePath": "api/Product/{id}",
    "HttpMethod": "GET",
    "IsController": true,
    "Order": 0,
    "Parameters": [
      {
        "Name": "id",
        "Type": "System.Int32",
        "IsRequired": true
      }
    ],
    "ReturnTypes": []
  },
  {
    "ContainingType": "ProSolution.API.Controllers.ProductController",
    "Method": "HardDelete",
    "RelativePath": "api/Product/{id}Hard",
    "HttpMethod": "DELETE",
    "IsController": true,
    "Order": 0,
    "Parameters": [
      {
        "Name": "id",
        "Type": "System.Int32",
        "IsRequired": true
      }
    ],
    "ReturnTypes": []
  },
  {
    "ContainingType": "ProSolution.API.Controllers.ProductController",
    "Method": "Restore",
    "RelativePath": "api/Product/{id}Restore",
    "HttpMethod": "PUT",
    "IsController": true,
    "Order": 0,
    "Parameters": [
      {
        "Name": "id",
        "Type": "System.Int32",
        "IsRequired": true
      }
    ],
    "ReturnTypes": []
  },
  {
    "ContainingType": "ProSolution.API.Controllers.ProductController",
    "Method": "SoftDelete",
    "RelativePath": "api/Product/{id}Soft",
    "HttpMethod": "DELETE",
    "IsController": true,
    "Order": 0,
    "Parameters": [
      {
        "Name": "id",
        "Type": "System.Int32",
        "IsRequired": true
      }
    ],
    "ReturnTypes": []
  },
  {
    "ContainingType": "ProSolution.API.Controllers.ProductController",
    "Method": "GetAllDeleted",
    "RelativePath": "api/Product/Deleted",
    "HttpMethod": "GET",
    "IsController": true,
    "Order": 0,
    "Parameters": [],
    "ReturnTypes": [
      {
        "Type": "System.Collections.Generic.ICollection\u00601[[ProSolution.BL.DTOs.ProductDTOs.ProductReadDTO, ProSolution.BL, Version=1.0.0.0, Culture=neutral, PublicKeyToken=null]]",
        "MediaTypes": [
          "text/plain",
          "application/json",
          "text/json"
        ],
        "StatusCode": 200
      }
    ]
  },
  {
    "ContainingType": "ProSolution.API.Controllers.ProductController",
    "Method": "GetAllDiscountProduct",
    "RelativePath": "api/Product/DiscountProduct",
    "HttpMethod": "GET",
    "IsController": true,
    "Order": 0,
    "Parameters": [],
    "ReturnTypes": [
      {
        "Type": "System.Collections.Generic.ICollection\u00601[[ProSolution.BL.DTOs.ProductDTOs.ProductReadDTO, ProSolution.BL, Version=1.0.0.0, Culture=neutral, PublicKeyToken=null]]",
        "MediaTypes": [
          "text/plain",
          "application/json",
          "text/json"
        ],
        "StatusCode": 200
      }
    ]
  },
  {
    "ContainingType": "ProSolution.API.Controllers.ProductController",
    "Method": "GetAllProductFilteredPrice",
    "RelativePath": "api/Product/FilterPriceProduct",
    "HttpMethod": "GET",
    "IsController": true,
    "Order": 0,
    "Parameters": [
      {
        "Name": "minPrice",
        "Type": "System.Int32",
        "IsRequired": false
      },
      {
        "Name": "maxPrice",
        "Type": "System.Int32",
        "IsRequired": false
      }
    ],
    "ReturnTypes": [
      {
        "Type": "System.Collections.Generic.ICollection\u00601[[ProSolution.BL.DTOs.ProductDTOs.ProductReadDTO, ProSolution.BL, Version=1.0.0.0, Culture=neutral, PublicKeyToken=null]]",
        "MediaTypes": [
          "text/plain",
          "application/json",
          "text/json"
        ],
        "StatusCode": 200
      }
    ]
  },
  {
    "ContainingType": "ProSolution.API.Controllers.ProductController",
    "Method": "GetAllMostSold",
    "RelativePath": "api/Product/MostSoldProduct",
    "HttpMethod": "GET",
    "IsController": true,
    "Order": 0,
    "Parameters": [],
    "ReturnTypes": [
      {
        "Type": "System.Collections.Generic.ICollection\u00601[[ProSolution.BL.DTOs.ProductDTOs.ProductReadDTO, ProSolution.BL, Version=1.0.0.0, Culture=neutral, PublicKeyToken=null]]",
        "MediaTypes": [
          "text/plain",
          "application/json",
          "text/json"
        ],
        "StatusCode": 200
      }
    ]
  },
  {
    "ContainingType": "ProSolution.API.Controllers.ProductController",
    "Method": "GetAllNewestDiscountProduct",
    "RelativePath": "api/Product/NewestDiscountProduct",
    "HttpMethod": "GET",
    "IsController": true,
    "Order": 0,
    "Parameters": [],
    "ReturnTypes": [
      {
        "Type": "System.Collections.Generic.ICollection\u00601[[ProSolution.BL.DTOs.ProductDTOs.ProductReadDTO, ProSolution.BL, Version=1.0.0.0, Culture=neutral, PublicKeyToken=null]]",
        "MediaTypes": [
          "text/plain",
          "application/json",
          "text/json"
        ],
        "StatusCode": 200
      }
    ]
  },
  {
    "ContainingType": "ProSolution.API.Controllers.ProductController",
    "Method": "GetNewestProduct",
    "RelativePath": "api/Product/NewestProduct",
    "HttpMethod": "GET",
    "IsController": true,
    "Order": 0,
    "Parameters": [],
    "ReturnTypes": [
      {
        "Type": "System.Collections.Generic.ICollection\u00601[[ProSolution.BL.DTOs.ProductDTOs.ProductReadDTO, ProSolution.BL, Version=1.0.0.0, Culture=neutral, PublicKeyToken=null]]",
        "MediaTypes": [
          "text/plain",
          "application/json",
          "text/json"
        ],
        "StatusCode": 200
      }
    ]
  },
  {
    "ContainingType": "ProSolution.API.Controllers.ProductController",
    "Method": "GetPaginated",
    "RelativePath": "api/Product/Paginated",
    "HttpMethod": "GET",
    "IsController": true,
    "Order": 0,
    "Parameters": [
      {
        "Name": "PageNumber",
        "Type": "System.Int32",
        "IsRequired": false
      },
      {
        "Name": "PageSize",
        "Type": "System.Int32",
        "IsRequired": false
      }
    ],
    "ReturnTypes": []
  },
  {
    "ContainingType": "ProSolution.API.Controllers.ProductController",
    "Method": "Search",
    "RelativePath": "api/Product/Search",
    "HttpMethod": "GET",
    "IsController": true,
    "Order": 0,
    "Parameters": [
      {
        "Name": "searchword",
        "Type": "System.String",
        "IsRequired": false
      }
    ],
    "ReturnTypes": []
  },
  {
    "ContainingType": "ProSolution.API.Controllers.ReviewController",
    "Method": "GetAll",
    "RelativePath": "api/Review",
    "HttpMethod": "GET",
    "IsController": true,
    "Order": 0,
    "Parameters": [],
    "ReturnTypes": [
      {
        "Type": "System.Collections.Generic.ICollection\u00601[[ProSolution.Core.Entities.Review, ProSolution.Core, Version=1.0.0.0, Culture=neutral, PublicKeyToken=null]]",
        "MediaTypes": [
          "text/plain",
          "application/json",
          "text/json"
        ],
        "StatusCode": 200
      }
    ]
  },
  {
    "ContainingType": "ProSolution.API.Controllers.ReviewController",
    "Method": "Create",
    "RelativePath": "api/Review",
    "HttpMethod": "POST",
    "IsController": true,
    "Order": 0,
    "Parameters": [
      {
        "Name": "Message",
        "Type": "System.String",
        "IsRequired": false
      },
      {
        "Name": "Name",
        "Type": "System.String",
        "IsRequired": false
      },
      {
        "Name": "Email",
        "Type": "System.String",
        "IsRequired": false
      },
      {
        "Name": "SaveMe",
        "Type": "System.Boolean",
        "IsRequired": false
      },
      {
        "Name": "ProductId",
        "Type": "System.Int32",
        "IsRequired": false
      },
      {
        "Name": "Raiting",
        "Type": "System.String",
        "IsRequired": false
      }
    ],
    "ReturnTypes": []
  },
  {
    "ContainingType": "ProSolution.API.Controllers.ReviewController",
    "Method": "GetById",
    "RelativePath": "api/Review/{id}",
    "HttpMethod": "GET",
    "IsController": true,
    "Order": 0,
    "Parameters": [
      {
        "Name": "id",
        "Type": "System.Int32",
        "IsRequired": true
      }
    ],
    "ReturnTypes": []
  },
  {
    "ContainingType": "ProSolution.API.Controllers.ReviewController",
    "Method": "Update",
    "RelativePath": "api/Review/{id}",
    "HttpMethod": "PUT",
    "IsController": true,
    "Order": 0,
    "Parameters": [
      {
        "Name": "id",
        "Type": "System.Int32",
        "IsRequired": true
      },
      {
        "Name": "catagoryDto",
        "Type": "ProSolution.BL.DTOs.ReviewDTOs.ReviewDTO",
        "IsRequired": true
      }
    ],
    "ReturnTypes": []
  },
  {
    "ContainingType": "ProSolution.API.Controllers.ReviewController",
    "Method": "HardDelete",
    "RelativePath": "api/Review/{id}Hard",
    "HttpMethod": "DELETE",
    "IsController": true,
    "Order": 0,
    "Parameters": [
      {
        "Name": "id",
        "Type": "System.Int32",
        "IsRequired": true
      }
    ],
    "ReturnTypes": []
  },
  {
    "ContainingType": "ProSolution.API.Controllers.ReviewController",
    "Method": "Restore",
    "RelativePath": "api/Review/{id}Restore",
    "HttpMethod": "PUT",
    "IsController": true,
    "Order": 0,
    "Parameters": [
      {
        "Name": "id",
        "Type": "System.Int32",
        "IsRequired": true
      }
    ],
    "ReturnTypes": []
  },
  {
    "ContainingType": "ProSolution.API.Controllers.ReviewController",
    "Method": "SoftDelete",
    "RelativePath": "api/Review/{id}Soft",
    "HttpMethod": "DELETE",
    "IsController": true,
    "Order": 0,
    "Parameters": [
      {
        "Name": "id",
        "Type": "System.Int32",
        "IsRequired": true
      }
    ],
    "ReturnTypes": []
  },
  {
    "ContainingType": "ProSolution.API.Controllers.ReviewController",
    "Method": "GetAllDeleted",
    "RelativePath": "api/Review/Deleted",
    "HttpMethod": "GET",
    "IsController": true,
    "Order": 0,
    "Parameters": [],
    "ReturnTypes": [
      {
        "Type": "System.Collections.Generic.ICollection\u00601[[ProSolution.Core.Entities.Review, ProSolution.Core, Version=1.0.0.0, Culture=neutral, PublicKeyToken=null]]",
        "MediaTypes": [
          "text/plain",
          "application/json",
          "text/json"
        ],
        "StatusCode": 200
      }
    ]
  },
  {
    "ContainingType": "ProSolution.API.Controllers.ReviewController",
    "Method": "GetPaginated",
    "RelativePath": "api/Review/Paginated",
    "HttpMethod": "GET",
    "IsController": true,
    "Order": 0,
    "Parameters": [
      {
        "Name": "PageNumber",
        "Type": "System.Int32",
        "IsRequired": false
      },
      {
        "Name": "PageSize",
        "Type": "System.Int32",
        "IsRequired": false
      },
      {
        "Name": "productId",
        "Type": "System.Nullable\u00601[[System.Int32, System.Private.CoreLib, Version=8.0.0.0, Culture=neutral, PublicKeyToken=7cec85d7bea7798e]]",
        "IsRequired": false
      }
    ],
    "ReturnTypes": []
  },
  {
    "ContainingType": "ProSolution.API.Controllers.SliderController",
    "Method": "GetAll",
    "RelativePath": "api/Slider",
    "HttpMethod": "GET",
    "IsController": true,
    "Order": 0,
    "Parameters": [],
    "ReturnTypes": [
      {
        "Type": "System.Collections.Generic.ICollection\u00601[[ProSolution.Core.Entities.Slider, ProSolution.Core, Version=1.0.0.0, Culture=neutral, PublicKeyToken=null]]",
        "MediaTypes": [
          "text/plain",
          "application/json",
          "text/json"
        ],
        "StatusCode": 200
      }
    ]
  },
  {
    "ContainingType": "ProSolution.API.Controllers.SliderController",
    "Method": "Create",
    "RelativePath": "api/Slider",
    "HttpMethod": "POST",
    "IsController": true,
    "Order": 0,
    "Parameters": [
      {
        "Name": "ImagePath",
        "Type": "Microsoft.AspNetCore.Http.IFormFile",
        "IsRequired": false
      }
    ],
    "ReturnTypes": []
  },
  {
    "ContainingType": "ProSolution.API.Controllers.SliderController",
    "Method": "GetById",
    "RelativePath": "api/Slider/{id}",
    "HttpMethod": "GET",
    "IsController": true,
    "Order": 0,
    "Parameters": [
      {
        "Name": "id",
        "Type": "System.Int32",
        "IsRequired": true
      }
    ],
    "ReturnTypes": []
  },
  {
    "ContainingType": "ProSolution.API.Controllers.SliderController",
    "Method": "Update",
    "RelativePath": "api/Slider/{id}",
    "HttpMethod": "PUT",
    "IsController": true,
    "Order": 0,
    "Parameters": [
      {
        "Name": "id",
        "Type": "System.Int32",
        "IsRequired": true
      },
      {
        "Name": "ImagePath",
        "Type": "Microsoft.AspNetCore.Http.IFormFile",
        "IsRequired": false
      }
    ],
    "ReturnTypes": []
  },
  {
    "ContainingType": "ProSolution.API.Controllers.SliderController",
    "Method": "HardDelete",
    "RelativePath": "api/Slider/{id}Hard",
    "HttpMethod": "DELETE",
    "IsController": true,
    "Order": 0,
    "Parameters": [
      {
        "Name": "id",
        "Type": "System.Int32",
        "IsRequired": true
      }
    ],
    "ReturnTypes": []
  },
  {
    "ContainingType": "ProSolution.API.Controllers.SliderController",
    "Method": "Restore",
    "RelativePath": "api/Slider/{id}Restore",
    "HttpMethod": "PUT",
    "IsController": true,
    "Order": 0,
    "Parameters": [
      {
        "Name": "id",
        "Type": "System.Int32",
        "IsRequired": true
      }
    ],
    "ReturnTypes": []
  },
  {
    "ContainingType": "ProSolution.API.Controllers.SliderController",
    "Method": "SoftDelete",
    "RelativePath": "api/Slider/{id}Soft",
    "HttpMethod": "DELETE",
    "IsController": true,
    "Order": 0,
    "Parameters": [
      {
        "Name": "id",
        "Type": "System.Int32",
        "IsRequired": true
      }
    ],
    "ReturnTypes": []
  },
  {
    "ContainingType": "ProSolution.API.Controllers.SliderController",
    "Method": "GetAllDeleted",
    "RelativePath": "api/Slider/Deleted",
    "HttpMethod": "GET",
    "IsController": true,
    "Order": 0,
    "Parameters": [],
    "ReturnTypes": [
      {
        "Type": "System.Collections.Generic.ICollection\u00601[[ProSolution.Core.Entities.Slider, ProSolution.Core, Version=1.0.0.0, Culture=neutral, PublicKeyToken=null]]",
        "MediaTypes": [
          "text/plain",
          "application/json",
          "text/json"
        ],
        "StatusCode": 200
      }
    ]
  },
  {
    "ContainingType": "ProSolution.API.Controllers.SliderController",
    "Method": "GetPaginated",
    "RelativePath": "api/Slider/Paginated",
    "HttpMethod": "GET",
    "IsController": true,
    "Order": 0,
    "Parameters": [
      {
        "Name": "PageNumber",
        "Type": "System.Int32",
        "IsRequired": false
      },
      {
        "Name": "PageSize",
        "Type": "System.Int32",
        "IsRequired": false
      }
    ],
    "ReturnTypes": []
  }
]